appget/__init__.py
appget/__main__.py
appget/appget.py
appget/cmd.py
appget/log.py
appget/system.py
appget-0.1.3.dist-info/LICENSE
appget-0.1.3.dist-info/METADATA
appget-0.1.3.dist-info/WHEEL
appget-0.1.3.dist-info/top_level.txt
appget-0.1.3.dist-info/RECORD
